AUTHORS
CHANGELOG.txt
DESCRIPTION
LICENSE
MANIFEST.in
README.rst
setup.py
flake8_snippets/__init__.py
flake8_snippets/flake8_snippets.py
flake8_snippets.egg-info/PKG-INFO
flake8_snippets.egg-info/SOURCES.txt
flake8_snippets.egg-info/dependency_links.txt
flake8_snippets.egg-info/entry_points.txt
flake8_snippets.egg-info/requires.txt
flake8_snippets.egg-info/top_level.txt