Metadata-Version: 1.0
Name: flake8-snippets
Version: 0.1
Summary: A flake8 extension to find any code snippets you don't like
Home-page: https://github.com/bitmazk/flake8-snippets
Author: Tobias Lorenz
Author-email: tobias.lorenz@bitmazk.com
License: The MIT License
Keywords: django,app,reusable,flake8,snippets,code,review
Platform: OS Independent
